dxi/__init__.py
dxi/_version.py
dxi/dxi.py
dxi/dxi_tool_base.py
dxi/_cli/__init__.py
dxi/_cli/_bookmark_cli.py
dxi/_cli/_branch_cli.py
dxi/_cli/_config_cli.py
dxi/_cli/_container_cli.py
dxi/_cli/_database_cli.py
dxi/_cli/_environment_cli.py
dxi/_cli/_group_cli.py
dxi/_cli/_snapshot_cli.py
dxi/_cli/_template_cli.py
dxi/_cli/_user_cli.py
dxi/_lib/__init__.py
dxi/_lib/click_util.py
dxi/_lib/dlpx_exceptions.py
dxi/_lib/dx_logging.py
dxi/_lib/dx_timeflow.py
dxi/_lib/dxi_constants.py
dxi/_lib/get_references.py
dxi/_lib/get_session.py
dxi/_lib/run_async.py
dxi/_lib/run_job.py
dxi/_lib/util.py
dxi/bookmark/__init__.py
dxi/bookmark/dxi_bookmark.py
dxi/branch/__init__.py
dxi/branch/dxi_branch.py
dxi/config/__init__.py
dxi/config/dxi_config.py
dxi/container/__init__.py
dxi/container/dxi_container.py
dxi/database/__init__.py
dxi/database/dxi_database.py
dxi/database/_internal_lib/__init__.py
dxi/database/_internal_lib/_dxi_db.py
dxi/database/_internal_lib/_dxi_ingest.py
dxi/database/_internal_lib/_dxi_provision.py
dxi/database/_internal_lib/_ingest_lib/__init__.py
dxi/database/_internal_lib/_ingest_lib/dsource_link.py
dxi/database/_internal_lib/_ingest_lib/dsource_link_ase.py
dxi/database/_internal_lib/_ingest_lib/dsource_link_mssql.py
dxi/database/_internal_lib/_ingest_lib/dsource_link_oracle.py
dxi/database/_internal_lib/_ingest_lib/dsource_link_oraclemt.py
dxi/database/_internal_lib/_mixins/__init__.py
dxi/database/_internal_lib/_mixins/_dxi_delete.py
dxi/database/_internal_lib/_mixins/_dxi_provision_dsource.py
dxi/database/_internal_lib/_mixins/_dxi_provision_vdb.py
dxi/database/_internal_lib/_mixins/_dxi_refresh.py
dxi/database/_internal_lib/_mixins/_dxi_rewind.py
dxi/environment/__init__.py
dxi/environment/dxi_environment.py
dxi/group/__init__.py
dxi/group/dxi_group.py
dxi/logs/__init__.py
dxi/snapshot/__init__.py
dxi/snapshot/dxi_snapshot.py
dxi/template/__init__.py
dxi/template/dxi_template.py
dxi/user/__init__.py
dxi/user/dxi_user.py
dxi-1.3.3.1.dist-info/METADATA
dxi-1.3.3.1.dist-info/WHEEL
dxi-1.3.3.1.dist-info/entry_points.txt
dxi-1.3.3.1.dist-info/top_level.txt
dxi-1.3.3.1.dist-info/RECORD
