Metadata-Version: 2.1
Name: dxi
Version: 1.3.3.1
Summary: Delphix Integration Library and CLI
Home-page: UNKNOWN
Author: Delphix Engineering
License: Apache 2
Keywords: dxi,delphix,delphix integration,delphix automation
Platform: UNKNOWN
Classifier: Development Status :: 5 - Production/Stable
Classifier: Intended Audience :: Developers
Classifier: Intended Audience :: System Administrators
Classifier: Topic :: Software Development :: Libraries :: Python Modules
Classifier: Topic :: Database
Classifier: Programming Language :: Python :: 3.7
Classifier: Programming Language :: Python :: 3.8
Classifier: Programming Language :: Python :: 3.9
Requires-Dist: click
Requires-Dist: certifi
Requires-Dist: delphixpy
Requires-Dist: python-dateutil
Requires-Dist: colorama
Requires-Dist: tabulate
Requires-Dist: cryptography
Requires-Dist: pytz
